{
  "name": "Properties",
  "path": "/",
  "sections": [
    {
      "__resolveType": "HeaderReal"
    },
    {
      "__resolveType": "banner_privia"
    },
    {
      "__resolveType": "website/sections/Rendering/Lazy.tsx",
      "section": {
        "__resolveType": "site/sections/TitleSection.tsx",
        "title": "Thrive With Privia",
        "description": "<p><span style=\"font-size: 14pt;\" data-mce-style=\"font-size: 14pt;\">Luxury Concierge Services for Living and Investing in Florida Real Estate</span></p>"
      }
    },
    {
      "__resolveType": "site/sections/Shelf.tsx",
      "propertiesList": {
        "__resolveType": "site/loaders/propertiesData.ts"
      },
      "property": {
        "address": "lorem",
        "price": "0393094",
        "cars": "90",
        "bathrooms": "2",
        "area": "281390",
        "image": {
          "src": "https://ozksgdmyrqcxcwhnbepg.supabase.co/storage/v1/object/public/assets/11997/d60342a9-305b-4f8a-bfe0-f765a8dc0e8f",
          "alt": "lorem"
        }
      },
      "showPriceText": true,
      "priceText": "Starts at"
    },
    {
      "__resolveType": "Footer"
    },
    {
      "__resolveType": "website/sections/Rendering/Lazy.tsx",
      "section": {
        "__resolveType": "website/sections/Seo/Seo.tsx",
        "title": "Privia"
      }
    }
  ],
  "seo": {
    "__resolveType": "website/sections/Seo/SeoV2.tsx"
  },
  "__resolveType": "website/pages/Page.tsx"
}